{
  "$type": "BS.InteractableHolder, Assembly-CSharp",
  "id": "HolderRackTop",
  "version": 3,
  "tagFilter": 1,
  "slots": [
    2,
    3,
    4
  ],
  "locked": false,
  "warnIfNotAllowed": false,
  "warnIfInUse": false,
  "warnIfLocked": false,
  "grabFromHandle": true,
  "allowTeleGrab": true,
  "hideFromFpv": false,
  "grabTeleport": 0,
  "disableObjectProximityHighlighter": false,
  "delegateToParentHolder": false,
  "audioContainerPath": "SnapDefault",
  "disableTouch": false,
  "highlighterView": 0,
  "highlighterViewHandFreeOnly": false,
  "highlighterPath": "Holder",
  "highlighterShowAxisLine": false,
  "highlighterShowAxisLineOnProximity": false,
  "highlightDefaultTitle": "Rack",
  "highlightDefaultDesignation": ""
}