{
  "$type": "BS.InteractableHolder, Assembly-CSharp",
  "id": "HolderHips",
  "version": 3,
  "tagFilter": 1,
  "slots": [
    2,
    3
  ],
  "locked": false,
  "warnIfNotAllowed": false,
  "warnIfInUse": false,
  "warnIfLocked": false,
  "grabFromHandle": true,
  "allowTeleGrab": false,
  "hideFromFpv": false,
  "grabTeleport": 0,
  "disableObjectProximityHighlighter": true,
  "delegateToParentHolder": false,
  "audioContainerPath": "SnapDefault",
  "disableTouch": true,
  "highlighterView": 0,
  "highlighterViewHandFreeOnly": false,
  "highlighterPath": "Holster",
  "highlighterShowAxisLine": false,
  "highlighterShowAxisLineOnProximity": false,
  "highlightDefaultTitle": "Holster",
  "highlightDefaultDesignation": ""
}