{
  "$type": "BS.CollisionData, Assembly-CSharp",
  "id": "Metal",
  "version": 3,
  "physicMaterials": [
    "Metal"
  ],
  "collidedPhysicMaterials": [],
  "parenting": 0,
  "align": 0,
  "rotation": 0,
  "standAlone": true,
  "defaultEnterFXId": "HitMetal",
  "defaultLoopFXId": "",
  "defaultExitFXId": "",
  "bluntHitFXId": "HitSwordOnWood",
  "slashHitFXId": "HitSwordOnMetal2",
  "slashEnterFXId": "",
  "slashLoopFXId": "",
  "slashExitFXId": "",
  "pierceHitFXId": "HitSwordOnMetal2",
  "pierceEnterFXId": "",
  "pierceLoopFXId": "",
  "pierceExitFXId": ""
}